README.md
setup.py
test_package_py/__init__.py
test_package_py/__main__.py
test_package_py/config.py
test_package_py/workshops.py
test_package_py.egg-info/PKG-INFO
test_package_py.egg-info/SOURCES.txt
test_package_py.egg-info/dependency_links.txt
test_package_py.egg-info/entry_points.txt
test_package_py.egg-info/requires.txt
test_package_py.egg-info/top_level.txt