Metadata-Version: 2.1
Name: test-package-py
Version: 0.0.3
Summary: Permite consumir el API de CodigoFacilito.
Home-page: https://github.com/Ollyxs/python_package_test
Author: Lucas Ollarce
Author-email: luk5ollarce@gmail.com
License: MIT
Keywords: codigofacilito,ollyxs
Platform: UNKNOWN
Classifier: Development Status :: 3 - Alpha
Classifier: Intended Audience :: Developers
Classifier: Topic :: Software Development :: Build Tools
Classifier: License :: OSI Approved :: MIT License
Classifier: Programming Language :: Python :: 3
